potime/__init__.py
potime/api/Time.py
potime/api/__init__.py
potime/api/decorator.py
tests/__init__.py
tests/test.py
potime-0.0.3.dist-info/LICENSE
potime-0.0.3.dist-info/METADATA
potime-0.0.3.dist-info/WHEEL
potime-0.0.3.dist-info/top_level.txt
potime-0.0.3.dist-info/RECORD
